licelfile/__init__.py
licelfile/licelfile.py
licelfile-0.1.3.dist-info/licenses/LICENCE.md
licelfile-0.1.3.dist-info/METADATA
licelfile-0.1.3.dist-info/WHEEL
licelfile-0.1.3.dist-info/top_level.txt
licelfile-0.1.3.dist-info/RECORD
